[
    {
        "nombre": "Gafas Luminosas LED Controladas por Voz",
        "precio": "S/43.40",
        "descuento": "No tiene descuento",
        "disponible": "Disponible"
    },
    {
        "nombre": "Soldador Eléctrico 110-220V 60W con 5 Puntas Intercambiables",
        "precio": "S/26.70",
        "descuento": "No tiene descuento",
        "disponible": "Disponible"
    },
    {
        "nombre": "Pegamento Conductor de Calor para Radiadores",
        "precio": "S/14.60",
        "descuento": "No tiene descuento",
        "disponible": "Disponible"
    },
    {
        "nombre": "Malla para desoldar 3mm HWY-3015",
        "precio": "S/8.60",
        "descuento": "No tiene descuento",
        "disponible": "Disponible"
    },
    {
        "nombre": "Estaño Super Solder Wire 0.8mm 60% 100gr Lotfett",
        "precio": "S/29.00",
        "descuento": "No tiene descuento",
        "disponible": "Disponible"
    },
    {
        "nombre": "Flux para Soldar 951 PCB FPC",
        "precio": "S/18.00",
        "descuento": "No tiene descuento",
        "disponible": "Disponible"
    },
    {
        "nombre": "Espuma Metálica para Limpiar Punta de Cautín",
        "precio": "S/14.00",
        "descuento": "No tiene descuento",
        "disponible": "Disponible"
    },
    {
        "nombre": "Punta para Cautín 60W – Goot",
        "precio": "S/35.00",
        "descuento": "-17%",
        "disponible": "No disponible"
    },
    {
        "nombre": "Punta para Cautín 30W",
        "precio": "S/5.50",
        "descuento": "No tiene descuento",
        "disponible": "Disponible"
    },
    {
        "nombre": "Cautín 60W 220Vac",
        "precio": "S/12.00",
        "descuento": "No tiene descuento",
        "disponible": "Disponible"
    },
    {
        "nombre": "Brocha Antiestática 14.3x4cm ESD",
        "precio": "S/5.00",
        "descuento": "No tiene descuento",
        "disponible": "Disponible"
    },
    {
        "nombre": "Estaño Super Solder Wire 0.8mm 60% 50gr Lotfett",
        "precio": "S/15.00",
        "descuento": "No tiene descuento",
        "disponible": "Disponible"
    },
    {
        "nombre": "Estaño para Soldar 0.8mm – 1m",
        "precio": "S/1.50",
        "descuento": "No tiene descuento",
        "disponible": "No disponible"
    },
    {
        "nombre": "Pulsera Antiestática ESD con Brazalete Metálico",
        "precio": "S/14.00",
        "descuento": "No tiene descuento",
        "disponible": "Disponible"
    },
    {
        "nombre": "Guantes Antiestáticos ESD de Fibra de Carbón",
        "precio": "S/5.00",
        "descuento": "-30%",
        "disponible": "Disponible"
    },
    {
        "nombre": "Kit de Soldadura Básica",
        "precio": "S/50.00",
        "descuento": "-2%",
        "disponible": "Disponible"
    },
    {
        "nombre": "Cautín 30W 220Vac",
        "precio": "S/20.00",
        "descuento": "-50%",
        "disponible": "Disponible"
    },
    {
        "nombre": "10 x Papel para Transferencia Térmica a PCB",
        "precio": "S/15.00",
        "descuento": "No tiene descuento",
        "disponible": "Disponible"
    },
    {
        "nombre": "Pasta de Soldar 50gr",
        "precio": "S/5.50",
        "descuento": "No tiene descuento",
        "disponible": "Disponible"
    },
    {
        "nombre": "Extractor Succionador de Estaño Metálico",
        "precio": "S/8.00",
        "descuento": "No tiene descuento",
        "disponible": "Disponible"
    },
    {
        "nombre": "Pulsera Antiestática ESD",
        "precio": "S/8.00",
        "descuento": "No tiene descuento",
        "disponible": "Disponible"
    },
    {
        "nombre": "SAIKE 898D Estación de Soldar",
        "precio": "S/280.00",
        "descuento": "-7%",
        "disponible": "No disponible"
    },
    {
        "nombre": "Soporte para Cautín",
        "precio": "S/11.00",
        "descuento": "-9%",
        "disponible": "Disponible"
    },
    {
        "nombre": "Pinzas ESD Acero Inoxidable",
        "precio": "S/22.00",
        "descuento": "No tiene descuento",
        "disponible": "Disponible"
    }
]